adumo/__init__.py
adumo/adumo.py
adumo/adumo_types.py
adumo/constants.py
adumo/exceptions.py
adumo/settings.py
adumo-0.1.15.dist-info/WHEEL
adumo-0.1.15.dist-info/METADATA
adumo-0.1.15.dist-info/RECORD
