Metadata-Version: 2.1
Name: adumo
Version: 0.1.15
Summary: 
Author: Wayne
Author-email: wayne@flickswitch.co.za
Requires-Python: >=3.9,<4.0
Classifier: Programming Language :: Python :: 3
Classifier: Programming Language :: Python :: 3.10
Classifier: Programming Language :: Python :: 3.9
Requires-Dist: environs (>=9.4.0,<10.0.0)
Requires-Dist: flake8 (>=4.0.1,<5.0.0)
Requires-Dist: httpx (>=0.21.3,<0.22.0)
